MANIFEST.in
Pipfile
Pipfile.lock
README.md
package_meta.py
setup.cfg
setup.py
bin/piston
bin/steempy
bin/steemtail
steem/__init__.py
steem/account.py
steem/aes.py
steem/amount.py
steem/block.py
steem/blockchain.py
steem/blog.py
steem/cli.py
steem/commit.py
steem/converter.py
steem/dex.py
steem/instance.py
steem/post.py
steem/profile.py
steem/steem.py
steem/steemd.py
steem/transactionbuilder.py
steem/utils.py
steem/wallet.py
steem/witness.py
steem_dshot.egg-info/PKG-INFO
steem_dshot.egg-info/SOURCES.txt
steem_dshot.egg-info/dependency_links.txt
steem_dshot.egg-info/requires.txt
steem_dshot.egg-info/top_level.txt
steembase/__init__.py
steembase/account.py
steembase/base58.py
steembase/bip38.py
steembase/chains.py
steembase/dictionary.py
steembase/exceptions.py
steembase/http_client.py
steembase/memo.py
steembase/operationids.py
steembase/operations.py
steembase/storage.py
steembase/transactions.py
steembase/types.py